SharedData/CacheRedis.py
SharedData/CollectionMongoDB.py
SharedData/Database.py
SharedData/Defaults.py
SharedData/Logger.py
SharedData/Metadata.py
SharedData/MultiProc.py
SharedData/OpenFIGI.py
SharedData/SharedData.py
SharedData/SharedNumpy.py
SharedData/StreamKafka.py
SharedData/Symbol.py
SharedData/Table.py
SharedData/TableDisk.py
SharedData/TableIndex.py
SharedData/TableIndexJit.py
SharedData/TableIndexJitFunctions.py
SharedData/TableIndexJitFunctionsManual.py
SharedData/TableIndexJitGenerate.py
SharedData/TableIndexJitHash.py
SharedData/TableIndexJitLoc.py
SharedData/TableMemory.py
SharedData/TimeSeriesDisk.py
SharedData/TimeSeriesMemory.py
SharedData/TimeseriesContainer.py
SharedData/Users.py
SharedData/Utils.py
SharedData/__init__.py
SharedData/sharedmutexwin.pyd
SharedData/API/ServerGunicorn.py
SharedData/API/ServerWaitress.py
SharedData/API/__init__.py
SharedData/API/auth.py
SharedData/API/constants.py
SharedData/API/utils.py
SharedData/API/routes/__init__.py
SharedData/API/routes/collections.py
SharedData/API/routes/metadata.py
SharedData/API/routes/system.py
SharedData/API/routes/tables.py
SharedData/API/routes/timeseries.py
SharedData/API/routes/workers.py
SharedData/IO/AWSEC2.py
SharedData/IO/AWSKinesis.py
SharedData/IO/AWSS3.py
SharedData/IO/AutoDocstrings.py
SharedData/IO/ClientAPI.py
SharedData/IO/ClientSocket.py
SharedData/IO/ClientWebSocket.py
SharedData/IO/LogHandlerAPI.py
SharedData/IO/MongoDBClient.py
SharedData/IO/ReadLogs.py
SharedData/IO/SaveTables.py
SharedData/IO/SendCommand.py
SharedData/IO/ServerAPI.py
SharedData/IO/ServerAPIDocs.yml
SharedData/IO/ServerAPI_Collection.py
SharedData/IO/ServerAPI_Common.py
SharedData/IO/ServerAPI_Table.py
SharedData/IO/ServerAPI_Timeseries.py
SharedData/IO/ServerAPI_Worker.py
SharedData/IO/ServerHttp.py
SharedData/IO/ServerSocket.py
SharedData/IO/ServerWebSocket.py
SharedData/IO/StreamsCache.py
SharedData/IO/StreamsPersist.py
SharedData/IO/SyncTable.py
SharedData/IO/TunnelWebSocket.py
shareddata-6.76.0.dist-info/LICENSE
shareddata-6.76.0.dist-info/METADATA
shareddata-6.76.0.dist-info/WHEEL
shareddata-6.76.0.dist-info/top_level.txt
shareddata-6.76.0.dist-info/RECORD
