Metadata-Version: 2.1
Name: shareddata
Version: 6.76.0
Summary: Memory Mapped / Shared Memory Database with S3 repository
Classifier: Programming Language :: Python :: 3
Classifier: License :: OSI Approved :: MIT License
Classifier: Operating System :: OS Independent
Requires-Python: >=3.9, <3.13
License-File: LICENSE
Requires-Dist: ipykernel ==6.23.3
Requires-Dist: boto3 ==1.26.160
Requires-Dist: python-json-logger ==2.0.7
Requires-Dist: python-dotenv ==1.0.0
Requires-Dist: pandas ==2.0.2
Requires-Dist: scipy ==1.14.0
Requires-Dist: numpy ==1.26.2
Requires-Dist: numba ==0.59.1
Requires-Dist: XlsxWriter ==3.1.2
Requires-Dist: openpyxl ==3.1.2
Requires-Dist: tqdm ==4.65.0
Requires-Dist: cffi ==1.17.1
Requires-Dist: tzlocal ==5.0.1
Requires-Dist: websockets ==12.0
Requires-Dist: cryptography ==41.0.7
Requires-Dist: lz4 ==4.3.3
Requires-Dist: flask ==3.0.0
Requires-Dist: waitress ==3.0.0
Requires-Dist: requests ==2.31.0
Requires-Dist: flasgger ==0.9.7.1
Requires-Dist: pymongo ==4.8.0
Requires-Dist: setuptools ==74.1.2
Requires-Dist: filelock ==3.18.0
Requires-Dist: gunicorn ==23.0.0
Requires-Dist: confluent-kafka ==2.10.0
Requires-Dist: aiokafka ==0.12.0
Requires-Dist: aiohttp ==3.12.13
Requires-Dist: redis ==6.2.0
